{
    "slug": "Shea-James--J",
    "candidateName": "Shea, James  J",
    "scrape_date": "2020-06-19",
    "officeTitle": "Supreme Court Justice No. 06",
    "partyDescr": "Non-Partisan",
    "periods": 4,
    "receipts": 12711.0,
    "expenditures": 5125.99,
    "balance": 7585.01,
    "summary": {
        "contributions": {
            "primary": 12711.0,
            "general": 0.0,
            "total": 12711.0
        },
        "expenditures": {
            "primary": 5125.99,
            "general": 0.0,
            "total": 5125.99
        },
        "cash_on_hand": {
            "primary": 7585.01,
            "general": 0.0,
            "total": 7585.01
        },
        "report_counts": {
            "C5": 4,
            "C7": 0,
            "C7E": 0
        }
    },
    "reports": [
        {
            "report": "05/15/2020 to 06/15/2020",
            "id": 48548,
            "type": "C5",
            "start_date": "05/15/2020",
            "end_date": "06/15/2020",
            "unitemized_contributions": 0.0,
            "num_contributions": 3,
            "num_expenditures": 2,
            "summary": {
                "previous report": {
                    "primary": 8156.38,
                    "general": 0.0,
                    "total": 8156.38
                },
                "Receipts": {
                    "primary": 450.0,
                    "general": 0.0,
                    "total": 450.0
                },
                "Expenditures": {
                    "primary": 1021.37,
                    "general": 0.0,
                    "total": 1021.37
                },
                "Ending Balance": {
                    "primary": 7585.01,
                    "general": 0.0,
                    "total": 7585.01
                },
                "report_start_date": "05/15/2020",
                "report_end_date": "06/15/2020"
            }
        },
        {
            "report": "04/16/2020 to 05/14/2020",
            "id": 47721,
            "type": "C5",
            "start_date": "04/16/2020",
            "end_date": "05/14/2020",
            "unitemized_contributions": 0.0,
            "num_contributions": 9,
            "num_expenditures": 3,
            "summary": {
                "previous report": {
                    "primary": 6971.83,
                    "general": 0.0,
                    "total": 6971.83
                },
                "Receipts": {
                    "primary": 1320.0,
                    "general": 0.0,
                    "total": 1320.0
                },
                "Expenditures": {
                    "primary": 135.45,
                    "general": 0.0,
                    "total": 135.45
                },
                "Ending Balance": {
                    "primary": 8156.38,
                    "general": 0.0,
                    "total": 8156.38
                },
                "report_start_date": "04/16/2020",
                "report_end_date": "05/14/2020"
            }
        },
        {
            "report": "03/16/2020 to 04/15/2020",
            "id": 46726,
            "type": "C5",
            "start_date": "03/16/2020",
            "end_date": "04/15/2020",
            "unitemized_contributions": 0.0,
            "num_contributions": 29,
            "num_expenditures": 6,
            "summary": {
                "previous report": {
                    "primary": 5991.75,
                    "general": 0.0,
                    "total": 5991.75
                },
                "Receipts": {
                    "primary": 4080.0,
                    "general": 0.0,
                    "total": 4080.0
                },
                "Expenditures": {
                    "primary": 3099.92,
                    "general": 0.0,
                    "total": 3099.92
                },
                "Ending Balance": {
                    "primary": 6971.83,
                    "general": 0.0,
                    "total": 6971.83
                },
                "report_start_date": "03/16/2020",
                "report_end_date": "04/15/2020"
            }
        },
        {
            "report": "01/01/2020 to 03/15/2020",
            "id": 46693,
            "type": "C5",
            "start_date": "01/01/2020",
            "end_date": "03/15/2020",
            "unitemized_contributions": 0.0,
            "num_contributions": 34,
            "num_expenditures": 13,
            "summary": {
                "previous report": {
                    "primary": 0.0,
                    "general": 0.0,
                    "total": 0.0
                },
                "Receipts": {
                    "primary": 6861.0,
                    "general": 0.0,
                    "total": 6861.0
                },
                "Expenditures": {
                    "primary": 869.25,
                    "general": 0.0,
                    "total": 869.25
                },
                "Ending Balance": {
                    "primary": 5991.75,
                    "general": 0.0,
                    "total": 5991.75
                },
                "report_start_date": "01/01/2020",
                "report_end_date": "03/15/2020"
            }
        }
    ]
}