{
    "data": {
        "reportId": 44795,
        "fromDateStr": "06/21/2018",
        "toDateStr": "11/21/2018",
        "formTypeCode": "C6",
        "formTypeDescr": "Political Committee Finance Report",
        "committeeId": 274,
        "candidateName": "Jefferson County Democratic Central Cmte.",
        "statusDescr": "Amended",
        "amendedDate": 1580067586000,
        "totalContrLessThan35": 0.0,
        "totalIndivContrLessThan35": 0.0,
        "grandTotalLessThan35": 0.0,
        "grandTotalLessThan35Primary": 0.0,
        "grandTotalLessThan35General": 0.0
    },
    "summary": {
        "start_date": "06/21/2018",
        "end_date": "11/21/2018",
        "receipts": 184.01,
        "expenditures": 1024.64,
        "cash_in_bank": 1678.19
    },
    "contributions": [
        {
            "Date Paid": "11/25/18",
            "Entity Name": "Coppinger, Roberta",
            "First Name": "",
            "Middle Initial": "",
            "Last Name": "",
            "Addr Line1": "P.O. Box 521",
            "City": "Whitehall",
            "State": "MT",
            "Zip": "59759",
            "Zip4": "",
            "Country": "",
            "Occupation": "Retired",
            "Employer": "NONE - RETIRED",
            "Contribution Type": "Individual Contributions",
            "Amount": 30.0,
            "Amount Type": "CA",
            "Purpose": "",
            "Election Type": "General",
            "Total Primary": 0.0,
            "Total General": 50.0,
            "Refund Transaction Type": "",
            "Refund Original Transaction Date": null,
            "Refund Original Transaction Total": 0.0,
            "Refund Original Transaction Descr": "",
            "Previous Transaction (Y/N)": "N",
            "Fundraiser Name": "",
            "Fundraiser Location": "",
            "Fundraiser Attendees": 0,
            "Fundraiser Tickets Sold": 0
        },
        {
            "Date Paid": "11/25/18",
            "Entity Name": "Herak, Bryher",
            "First Name": "",
            "Middle Initial": "",
            "Last Name": "",
            "Addr Line1": "PO  Box 5",
            "City": "Basin",
            "State": "MT",
            "Zip": "59631",
            "Zip4": "",
            "Country": "",
            "Occupation": "Retired",
            "Employer": "NONE - RETIRED",
            "Contribution Type": "Individual Contributions",
            "Amount": 100.0,
            "Amount Type": "CA",
            "Purpose": "",
            "Election Type": "General",
            "Total Primary": 0.0,
            "Total General": 100.0,
            "Refund Transaction Type": "",
            "Refund Original Transaction Date": null,
            "Refund Original Transaction Total": 0.0,
            "Refund Original Transaction Descr": "",
            "Previous Transaction (Y/N)": "N",
            "Fundraiser Name": "",
            "Fundraiser Location": "",
            "Fundraiser Attendees": 0,
            "Fundraiser Tickets Sold": 0
        }
    ],
    "expenditures": [
        {
            "Date Paid": "07/20/18",
            "Entity Name": "Evans, Melody",
            "First Name": "",
            "Middle Initial": "",
            "Last Name": "",
            "Addr Line1": "PO Box 152",
            "City": "Whitehall",
            "State": "MT",
            "Zip": "59759",
            "Zip4": "",
            "Expenditure Type": "All Other Expenditures",
            "Amount": 66.98,
            "Purpose": "reimburse for purchase of 2 bags of bead necklaces, 6 pounds of candy for booth at Whitehall Frontier Days",
            "Election Type": "General",
            "Expenditure Paid Communications Platform": "",
            "Expenditure Paid Communications Quantity": "",
            "Expenditure Paid Communications Subject Matter": ""
        },
        {
            "Date Paid": "07/13/18",
            "Entity Name": "Insty Prints",
            "First Name": "",
            "Middle Initial": "",
            "Last Name": "",
            "Addr Line1": "120 W Park",
            "City": "Butte",
            "State": "MT",
            "Zip": "59701",
            "Zip4": "",
            "Expenditure Type": "All Other Expenditures",
            "Amount": 42.0,
            "Purpose": "1- 2x6 Jefferson County Democratic party banner",
            "Election Type": "General",
            "Expenditure Paid Communications Platform": "",
            "Expenditure Paid Communications Quantity": "",
            "Expenditure Paid Communications Subject Matter": ""
        },
        {
            "Date Paid": "08/28/18",
            "Entity Name": "Jefferson County Clerk & Recorder",
            "First Name": "",
            "Middle Initial": "",
            "Last Name": "",
            "Addr Line1": "Po Box H",
            "City": "Boulder",
            "State": "MT",
            "Zip": "59632",
            "Zip4": "",
            "Expenditure Type": "All Other Expenditures",
            "Amount": 50.0,
            "Purpose": "Room rent for monthly meeting",
            "Election Type": "General",
            "Expenditure Paid Communications Platform": "",
            "Expenditure Paid Communications Quantity": "",
            "Expenditure Paid Communications Subject Matter": ""
        },
        {
            "Date Paid": "11/14/18",
            "Entity Name": "Jefferson County Clerk & Recorder",
            "First Name": "",
            "Middle Initial": "",
            "Last Name": "",
            "Addr Line1": "Po Box H",
            "City": "Boulder",
            "State": "MT",
            "Zip": "59632",
            "Zip4": "",
            "Expenditure Type": "All Other Expenditures",
            "Amount": 50.0,
            "Purpose": "Monthly meeting location rent",
            "Election Type": "General",
            "Expenditure Paid Communications Platform": "",
            "Expenditure Paid Communications Quantity": "",
            "Expenditure Paid Communications Subject Matter": ""
        },
        {
            "Date Paid": "06/29/18",
            "Entity Name": "Jefferson County Treasurer",
            "First Name": "",
            "Middle Initial": "",
            "Last Name": "",
            "Addr Line1": "201 Centennial",
            "City": "Boulder",
            "State": "MT",
            "Zip": "59632",
            "Zip4": "",
            "Expenditure Type": "All Other Expenditures",
            "Amount": 40.0,
            "Purpose": "Booth rental at Jefferson County Fair - one day",
            "Election Type": "General",
            "Expenditure Paid Communications Platform": "",
            "Expenditure Paid Communications Quantity": "",
            "Expenditure Paid Communications Subject Matter": ""
        },
        {
            "Date Paid": "10/05/18",
            "Entity Name": "Jefferson Fresh Foods",
            "First Name": "",
            "Middle Initial": "",
            "Last Name": "",
            "Addr Line1": "2 MT-2 West",
            "City": "Whitehall",
            "State": "MT",
            "Zip": "59759",
            "Zip4": "",
            "Expenditure Type": "All Other Expenditures",
            "Amount": 16.44,
            "Purpose": "refreshments for October committee meeting",
            "Election Type": "General",
            "Expenditure Paid Communications Platform": "",
            "Expenditure Paid Communications Quantity": "",
            "Expenditure Paid Communications Subject Matter": ""
        },
        {
            "Date Paid": "09/07/18",
            "Entity Name": "Jefferson Fresh Foods",
            "First Name": "",
            "Middle Initial": "",
            "Last Name": "",
            "Addr Line1": "2 MT-2 West",
            "City": "Whitehall",
            "State": "MT",
            "Zip": "59759",
            "Zip4": "",
            "Expenditure Type": "All Other Expenditures",
            "Amount": 22.22,
            "Purpose": "Refreshments for September County Committe meeting",
            "Election Type": "General",
            "Expenditure Paid Communications Platform": "",
            "Expenditure Paid Communications Quantity": "",
            "Expenditure Paid Communications Subject Matter": ""
        },
        {
            "Date Paid": "10/10/18",
            "Entity Name": "Johnson, Rebecca",
            "First Name": "",
            "Middle Initial": "",
            "Last Name": "",
            "Addr Line1": "PMB 2216, 1 Jackson Creek Rd.",
            "City": "Clancy",
            "State": "MT",
            "Zip": "59632",
            "Zip4": "",
            "Expenditure Type": "All Other Expenditures",
            "Amount": 200.0,
            "Purpose": "Reimbursement for housing and tickets for Platform convention",
            "Election Type": "General",
            "Expenditure Paid Communications Platform": "",
            "Expenditure Paid Communications Quantity": "",
            "Expenditure Paid Communications Subject Matter": ""
        },
        {
            "Date Paid": "08/02/18",
            "Entity Name": "USPS",
            "First Name": "",
            "Middle Initial": "",
            "Last Name": "",
            "Addr Line1": "15 N. Main St",
            "City": "Whitehall",
            "State": "MT",
            "Zip": "59759",
            "Zip4": "",
            "Expenditure Type": "All Other Expenditures",
            "Amount": 27.0,
            "Purpose": "Post Office Box Rental 6 months",
            "Election Type": "General",
            "Expenditure Paid Communications Platform": "",
            "Expenditure Paid Communications Quantity": "",
            "Expenditure Paid Communications Subject Matter": ""
        },
        {
            "Date Paid": "07/28/18",
            "Entity Name": "Whitehall Chamber of Commerce",
            "First Name": "",
            "Middle Initial": "",
            "Last Name": "",
            "Addr Line1": "501 N. Whitehall St.",
            "City": "Whitehall",
            "State": "MT",
            "Zip": "59759",
            "Zip4": "",
            "Expenditure Type": "All Other Expenditures",
            "Amount": 35.0,
            "Purpose": "Frontier Day Booth Rental ",
            "Election Type": "General",
            "Expenditure Paid Communications Platform": "",
            "Expenditure Paid Communications Quantity": "",
            "Expenditure Paid Communications Subject Matter": ""
        },
        {
            "Date Paid": "09/08/18",
            "Entity Name": "Whitehall Farmers Market",
            "First Name": "",
            "Middle Initial": "",
            "Last Name": "",
            "Addr Line1": "Box 761 ",
            "City": "Whitehall",
            "State": "MT",
            "Zip": "59759",
            "Zip4": "",
            "Expenditure Type": "All Other Expenditures",
            "Amount": 5.0,
            "Purpose": "Booth rental at farmers market",
            "Election Type": "General",
            "Expenditure Paid Communications Platform": "",
            "Expenditure Paid Communications Quantity": "",
            "Expenditure Paid Communications Subject Matter": ""
        },
        {
            "Date Paid": "08/28/18",
            "Entity Name": "Whitehall Farmers Market",
            "First Name": "",
            "Middle Initial": "",
            "Last Name": "",
            "Addr Line1": "Box 761 ",
            "City": "Whitehall",
            "State": "MT",
            "Zip": "59759",
            "Zip4": "",
            "Expenditure Type": "All Other Expenditures",
            "Amount": 5.0,
            "Purpose": "Booth space rental for 9/1 market",
            "Election Type": "General",
            "Expenditure Paid Communications Platform": "",
            "Expenditure Paid Communications Quantity": "",
            "Expenditure Paid Communications Subject Matter": ""
        },
        {
            "Date Paid": "09/15/18",
            "Entity Name": "Whitehall Farmers Market",
            "First Name": "",
            "Middle Initial": "",
            "Last Name": "",
            "Addr Line1": "Box 761 ",
            "City": "Whitehall",
            "State": "MT",
            "Zip": "59759",
            "Zip4": "",
            "Expenditure Type": "All Other Expenditures",
            "Amount": 5.0,
            "Purpose": "9/15 booth space rental at farmers market ",
            "Election Type": "General",
            "Expenditure Paid Communications Platform": "",
            "Expenditure Paid Communications Quantity": "",
            "Expenditure Paid Communications Subject Matter": ""
        },
        {
            "Date Paid": "09/22/18",
            "Entity Name": "Whitehall Farmers Market",
            "First Name": "",
            "Middle Initial": "",
            "Last Name": "",
            "Addr Line1": "Box 761 ",
            "City": "Whitehall",
            "State": "MT",
            "Zip": "59759",
            "Zip4": "",
            "Expenditure Type": "All Other Expenditures",
            "Amount": 5.0,
            "Purpose": "9/22 booth rental at farmers market",
            "Election Type": "General",
            "Expenditure Paid Communications Platform": "",
            "Expenditure Paid Communications Quantity": "",
            "Expenditure Paid Communications Subject Matter": ""
        },
        {
            "Date Paid": "09/29/18",
            "Entity Name": "Whitehall Farmers Market",
            "First Name": "",
            "Middle Initial": "",
            "Last Name": "",
            "Addr Line1": "Box 761 ",
            "City": "Whitehall",
            "State": "MT",
            "Zip": "59759",
            "Zip4": "",
            "Expenditure Type": "All Other Expenditures",
            "Amount": 5.0,
            "Purpose": "9/29 booth rental for farmers market",
            "Election Type": "General",
            "Expenditure Paid Communications Platform": "",
            "Expenditure Paid Communications Quantity": "",
            "Expenditure Paid Communications Subject Matter": ""
        },
        {
            "Date Paid": "10/06/18",
            "Entity Name": "Bryher Herak for HD 75 Campaign",
            "First Name": "",
            "Middle Initial": "",
            "Last Name": "",
            "Addr Line1": "Box 97",
            "City": "Basin",
            "State": "MT",
            "Zip": "59631",
            "Zip4": "",
            "Expenditure Type": "Independent Expenditure",
            "Amount": 450.0,
            "Purpose": "Support Bryher Herak Campaign",
            "Election Type": "General",
            "Expenditure Paid Communications Platform": "",
            "Expenditure Paid Communications Quantity": "",
            "Expenditure Paid Communications Subject Matter": ""
        }
    ]
}