{
    "data": {
        "reportId": 33907,
        "fromDateStr": "01/01/2015",
        "toDateStr": "12/31/2015",
        "formTypeCode": "C6",
        "formTypeDescr": "Political Committee Finance Report",
        "committeeId": 237,
        "candidateName": "Chouteau County Republican Central Cmte.",
        "statusDescr": "Amended",
        "amendedDate": 1593182654000,
        "totalContrLessThan35": 0.0,
        "totalIndivContrLessThan35": 0.0,
        "grandTotalLessThan35": 0.0,
        "grandTotalLessThan35Primary": 0.0,
        "grandTotalLessThan35General": 0.0
    },
    "summary": {
        "start_date": "01/01/2015",
        "end_date": "12/31/2015",
        "receipts": 5641.0,
        "expenditures": 3501.0,
        "cash_in_bank": 7323.7
    },
    "contributions": [
        {
            "Date Paid": "01/05/16",
            "Entity Name": "hagan, roger a",
            "First Name": "",
            "Middle Initial": "",
            "Last Name": "",
            "Addr Line1": "117 gerber rd",
            "City": "great falls",
            "State": "MT",
            "Zip": "59405",
            "Zip4": "",
            "Country": "",
            "Occupation": "Retired",
            "Employer": "RETIRED",
            "Contribution Type": "Individual Contributions",
            "Amount": 350.0,
            "Amount Type": "CA",
            "Purpose": "",
            "Election Type": "Primary",
            "Total Primary": 350.0,
            "Total General": 0.0,
            "Refund Transaction Type": "",
            "Refund Original Transaction Date": null,
            "Refund Original Transaction Total": 0.0,
            "Refund Original Transaction Descr": "",
            "Previous Transaction (Y/N)": "N",
            "Fundraiser Name": "",
            "Fundraiser Location": "",
            "Fundraiser Attendees": 0,
            "Fundraiser Tickets Sold": 0
        },
        {
            "Date Paid": "01/26/16",
            "Entity Name": "Hollandsworth, Roy G",
            "First Name": "",
            "Middle Initial": "",
            "Last Name": "",
            "Addr Line1": "1463 Prairie Dr.",
            "City": "Brady",
            "State": "MT",
            "Zip": "59416",
            "Zip4": "",
            "Country": "",
            "Occupation": "FARMER",
            "Employer": "self",
            "Contribution Type": "Individual Contributions",
            "Amount": 55.0,
            "Amount Type": "CA",
            "Purpose": "",
            "Election Type": "Primary",
            "Total Primary": 55.0,
            "Total General": 0.0,
            "Refund Transaction Type": "",
            "Refund Original Transaction Date": null,
            "Refund Original Transaction Total": 0.0,
            "Refund Original Transaction Descr": "",
            "Previous Transaction (Y/N)": "N",
            "Fundraiser Name": "",
            "Fundraiser Location": "",
            "Fundraiser Attendees": 0,
            "Fundraiser Tickets Sold": 0
        },
        {
            "Date Paid": "01/26/16",
            "Entity Name": "jensen, ronald",
            "First Name": "",
            "Middle Initial": "",
            "Last Name": "",
            "Addr Line1": "1719 Washington",
            "City": "Fort Benton",
            "State": "MT",
            "Zip": "59442",
            "Zip4": "",
            "Country": "",
            "Occupation": "Farmer",
            "Employer": "SELF - Ranch Owner",
            "Contribution Type": "Individual Contributions",
            "Amount": 382.0,
            "Amount Type": "CA",
            "Purpose": "",
            "Election Type": "Primary",
            "Total Primary": 382.0,
            "Total General": 0.0,
            "Refund Transaction Type": "",
            "Refund Original Transaction Date": null,
            "Refund Original Transaction Total": 0.0,
            "Refund Original Transaction Descr": "",
            "Previous Transaction (Y/N)": "N",
            "Fundraiser Name": "",
            "Fundraiser Location": "",
            "Fundraiser Attendees": 0,
            "Fundraiser Tickets Sold": 0
        },
        {
            "Date Paid": "01/26/16",
            "Entity Name": "Rominger, Dean",
            "First Name": "",
            "Middle Initial": "",
            "Last Name": "",
            "Addr Line1": "449 Rominger Lane",
            "City": "Floweree",
            "State": "MT",
            "Zip": "59440",
            "Zip4": "",
            "Country": "",
            "Occupation": "FARMER",
            "Employer": "SELF",
            "Contribution Type": "Individual Contributions",
            "Amount": 125.0,
            "Amount Type": "CA",
            "Purpose": "",
            "Election Type": "Primary",
            "Total Primary": 125.0,
            "Total General": 0.0,
            "Refund Transaction Type": "",
            "Refund Original Transaction Date": null,
            "Refund Original Transaction Total": 0.0,
            "Refund Original Transaction Descr": "",
            "Previous Transaction (Y/N)": "N",
            "Fundraiser Name": "",
            "Fundraiser Location": "",
            "Fundraiser Attendees": 0,
            "Fundraiser Tickets Sold": 0
        },
        {
            "Date Paid": "01/26/16",
            "Entity Name": "Witt, Lani",
            "First Name": "",
            "Middle Initial": "",
            "Last Name": "",
            "Addr Line1": "1801 4th Ave North",
            "City": "Great Falls",
            "State": "MT",
            "Zip": "59401",
            "Zip4": "",
            "Country": "",
            "Occupation": "RANCHER",
            "Employer": "SELF - Ranch Owner",
            "Contribution Type": "Individual Contributions",
            "Amount": 768.0,
            "Amount Type": "CA",
            "Purpose": "",
            "Election Type": "Primary",
            "Total Primary": 768.0,
            "Total General": 0.0,
            "Refund Transaction Type": "",
            "Refund Original Transaction Date": null,
            "Refund Original Transaction Total": 0.0,
            "Refund Original Transaction Descr": "",
            "Previous Transaction (Y/N)": "N",
            "Fundraiser Name": "",
            "Fundraiser Location": "",
            "Fundraiser Attendees": 0,
            "Fundraiser Tickets Sold": 0
        },
        {
            "Date Paid": "01/26/16",
            "Entity Name": "Worrall, Diane K",
            "First Name": "",
            "Middle Initial": "",
            "Last Name": "",
            "Addr Line1": "PO Box 181",
            "City": "Loma",
            "State": "MT",
            "Zip": "59460",
            "Zip4": "",
            "Country": "",
            "Occupation": "FARMER MANAGER",
            "Employer": "SELF- EMPLOYED",
            "Contribution Type": "Individual Contributions",
            "Amount": 600.0,
            "Amount Type": "CA",
            "Purpose": "",
            "Election Type": "Primary",
            "Total Primary": 600.0,
            "Total General": 0.0,
            "Refund Transaction Type": "",
            "Refund Original Transaction Date": null,
            "Refund Original Transaction Total": 0.0,
            "Refund Original Transaction Descr": "",
            "Previous Transaction (Y/N)": "N",
            "Fundraiser Name": "",
            "Fundraiser Location": "",
            "Fundraiser Attendees": 0,
            "Fundraiser Tickets Sold": 0
        },
        {
            "Date Paid": "02/14/15",
            "Entity Name": "Lincoln Reagan Day Dinner",
            "First Name": "",
            "Middle Initial": "",
            "Last Name": "",
            "Addr Line1": "Various",
            "City": "Various",
            "State": "",
            "Zip": "",
            "Zip4": "",
            "Country": "",
            "Occupation": "",
            "Employer": "",
            "Contribution Type": "Interest, Rebates, Refunds, Fundraisers, and Other Miscellaneous Receipts",
            "Amount": -2430.0,
            "Amount Type": "CA",
            "Purpose": "fundraiser for committee",
            "Election Type": "General",
            "Total Primary": 0.0,
            "Total General": 3361.0,
            "Refund Transaction Type": "",
            "Refund Original Transaction Date": null,
            "Refund Original Transaction Total": 0.0,
            "Refund Original Transaction Descr": "",
            "Previous Transaction (Y/N)": "N",
            "Fundraiser Name": "",
            "Fundraiser Location": "",
            "Fundraiser Attendees": 0,
            "Fundraiser Tickets Sold": 0
        },
        {
            "Date Paid": "02/14/15",
            "Entity Name": "Lincoln Reagan Day Dinner",
            "First Name": "",
            "Middle Initial": "",
            "Last Name": "",
            "Addr Line1": "Various",
            "City": "Various",
            "State": "",
            "Zip": "",
            "Zip4": "",
            "Country": "",
            "Occupation": "",
            "Employer": "",
            "Contribution Type": "Interest, Rebates, Refunds, Fundraisers, and Other Miscellaneous Receipts",
            "Amount": -590.0,
            "Amount Type": "CA",
            "Purpose": "FUNDRAISER",
            "Election Type": "General",
            "Total Primary": 0.0,
            "Total General": 3361.0,
            "Refund Transaction Type": "",
            "Refund Original Transaction Date": null,
            "Refund Original Transaction Total": 0.0,
            "Refund Original Transaction Descr": "",
            "Previous Transaction (Y/N)": "N",
            "Fundraiser Name": "",
            "Fundraiser Location": "",
            "Fundraiser Attendees": 0,
            "Fundraiser Tickets Sold": 0
        },
        {
            "Date Paid": "02/14/15",
            "Entity Name": "Lincoln Reagan Day Dinner",
            "First Name": "",
            "Middle Initial": "",
            "Last Name": "",
            "Addr Line1": "Various",
            "City": "Various",
            "State": "",
            "Zip": "",
            "Zip4": "",
            "Country": "",
            "Occupation": "",
            "Employer": "",
            "Contribution Type": "Interest, Rebates, Refunds, Fundraisers, and Other Miscellaneous Receipts",
            "Amount": -341.0,
            "Amount Type": "CA",
            "Purpose": "FUNDRAISER",
            "Election Type": "General",
            "Total Primary": 0.0,
            "Total General": 3361.0,
            "Refund Transaction Type": "",
            "Refund Original Transaction Date": null,
            "Refund Original Transaction Total": 0.0,
            "Refund Original Transaction Descr": "",
            "Previous Transaction (Y/N)": "N",
            "Fundraiser Name": "",
            "Fundraiser Location": "",
            "Fundraiser Attendees": 0,
            "Fundraiser Tickets Sold": 0
        }
    ],
    "expenditures": [
        {
            "Date Paid": "02/15/15",
            "Entity Name": "Bomgardners Catering",
            "First Name": "",
            "Middle Initial": "",
            "Last Name": "",
            "Addr Line1": "PO Box 112",
            "City": "Loma",
            "State": "MT",
            "Zip": "59460",
            "Zip4": "",
            "Expenditure Type": "All Other Expenditures",
            "Amount": 1350.0,
            "Purpose": "Catering Expense",
            "Election Type": "General",
            "Expenditure Paid Communications Platform": "",
            "Expenditure Paid Communications Quantity": "",
            "Expenditure Paid Communications Subject Matter": ""
        },
        {
            "Date Paid": "02/11/15",
            "Entity Name": "Emy Rominger",
            "First Name": "",
            "Middle Initial": "",
            "Last Name": "",
            "Addr Line1": "449 Rominger Ln.",
            "City": "Floweree",
            "State": "MT",
            "Zip": "59440",
            "Zip4": "",
            "Expenditure Type": "All Other Expenditures",
            "Amount": 134.62,
            "Purpose": "reinbursement to Emy Rominger for office supplies and LDD supplies",
            "Election Type": "General",
            "Expenditure Paid Communications Platform": "",
            "Expenditure Paid Communications Quantity": "",
            "Expenditure Paid Communications Subject Matter": ""
        },
        {
            "Date Paid": "12/16/15",
            "Entity Name": "First Security Bank",
            "First Name": "",
            "Middle Initial": "",
            "Last Name": "",
            "Addr Line1": "1502 Main St. ",
            "City": "Fort Benton",
            "State": "MT",
            "Zip": "59442",
            "Zip4": "",
            "Expenditure Type": "All Other Expenditures",
            "Amount": 2.0,
            "Purpose": "Service Charge",
            "Election Type": "General",
            "Expenditure Paid Communications Platform": "",
            "Expenditure Paid Communications Quantity": "",
            "Expenditure Paid Communications Subject Matter": ""
        },
        {
            "Date Paid": "07/15/15",
            "Entity Name": "First Security Bank",
            "First Name": "",
            "Middle Initial": "",
            "Last Name": "",
            "Addr Line1": "1502 Main St. ",
            "City": "Fort Benton",
            "State": "MT",
            "Zip": "59442",
            "Zip4": "",
            "Expenditure Type": "All Other Expenditures",
            "Amount": 2.0,
            "Purpose": "Service Charge",
            "Election Type": "General",
            "Expenditure Paid Communications Platform": "",
            "Expenditure Paid Communications Quantity": "",
            "Expenditure Paid Communications Subject Matter": ""
        },
        {
            "Date Paid": "10/21/15",
            "Entity Name": "First Security Bank",
            "First Name": "",
            "Middle Initial": "",
            "Last Name": "",
            "Addr Line1": "1502 Main St. ",
            "City": "Fort Benton",
            "State": "MT",
            "Zip": "59442",
            "Zip4": "",
            "Expenditure Type": "All Other Expenditures",
            "Amount": 2.0,
            "Purpose": "Service Charge",
            "Election Type": "General",
            "Expenditure Paid Communications Platform": "",
            "Expenditure Paid Communications Quantity": "",
            "Expenditure Paid Communications Subject Matter": ""
        },
        {
            "Date Paid": "09/16/15",
            "Entity Name": "First Security Bank",
            "First Name": "",
            "Middle Initial": "",
            "Last Name": "",
            "Addr Line1": "1502 Main St. ",
            "City": "Fort Benton",
            "State": "MT",
            "Zip": "59442",
            "Zip4": "",
            "Expenditure Type": "All Other Expenditures",
            "Amount": 2.0,
            "Purpose": "Service Charge",
            "Election Type": "General",
            "Expenditure Paid Communications Platform": "",
            "Expenditure Paid Communications Quantity": "",
            "Expenditure Paid Communications Subject Matter": ""
        },
        {
            "Date Paid": "11/18/15",
            "Entity Name": "First Security Bank",
            "First Name": "",
            "Middle Initial": "",
            "Last Name": "",
            "Addr Line1": "1502 Main St. ",
            "City": "Fort Benton",
            "State": "MT",
            "Zip": "59442",
            "Zip4": "",
            "Expenditure Type": "All Other Expenditures",
            "Amount": 2.0,
            "Purpose": "Service Charge",
            "Election Type": "General",
            "Expenditure Paid Communications Platform": "",
            "Expenditure Paid Communications Quantity": "",
            "Expenditure Paid Communications Subject Matter": ""
        },
        {
            "Date Paid": "08/19/15",
            "Entity Name": "First Security Bank",
            "First Name": "",
            "Middle Initial": "",
            "Last Name": "",
            "Addr Line1": "1502 Main St. ",
            "City": "Fort Benton",
            "State": "MT",
            "Zip": "59442",
            "Zip4": "",
            "Expenditure Type": "All Other Expenditures",
            "Amount": 2.0,
            "Purpose": "Service Charge",
            "Election Type": "General",
            "Expenditure Paid Communications Platform": "",
            "Expenditure Paid Communications Quantity": "",
            "Expenditure Paid Communications Subject Matter": ""
        },
        {
            "Date Paid": "06/17/15",
            "Entity Name": "First Security Bank",
            "First Name": "",
            "Middle Initial": "",
            "Last Name": "",
            "Addr Line1": "1502 Main St. ",
            "City": "Fort Benton",
            "State": "MT",
            "Zip": "59442",
            "Zip4": "",
            "Expenditure Type": "All Other Expenditures",
            "Amount": 2.0,
            "Purpose": "Service Charge",
            "Election Type": "General",
            "Expenditure Paid Communications Platform": "",
            "Expenditure Paid Communications Quantity": "",
            "Expenditure Paid Communications Subject Matter": ""
        },
        {
            "Date Paid": "02/24/15",
            "Entity Name": "Food Farms",
            "First Name": "",
            "Middle Initial": "",
            "Last Name": "",
            "Addr Line1": "1518 Front St.",
            "City": "Fort Benton",
            "State": "MT",
            "Zip": "59442",
            "Zip4": "",
            "Expenditure Type": "All Other Expenditures",
            "Amount": 105.81,
            "Purpose": "Lincoln Reagan Day Dinner (Food)",
            "Election Type": "General",
            "Expenditure Paid Communications Platform": "",
            "Expenditure Paid Communications Quantity": "",
            "Expenditure Paid Communications Subject Matter": ""
        },
        {
            "Date Paid": "02/09/15",
            "Entity Name": "IPS",
            "First Name": "",
            "Middle Initial": "",
            "Last Name": "",
            "Addr Line1": "92 2nd St. S.",
            "City": "Great Falls",
            "State": "MT",
            "Zip": "59403",
            "Zip4": "",
            "Expenditure Type": "All Other Expenditures",
            "Amount": 1.92,
            "Purpose": "PRINTING/MAILING",
            "Election Type": "General",
            "Expenditure Paid Communications Platform": "",
            "Expenditure Paid Communications Quantity": "",
            "Expenditure Paid Communications Subject Matter": ""
        },
        {
            "Date Paid": "01/27/15",
            "Entity Name": "Jim O'Hara",
            "First Name": "",
            "Middle Initial": "",
            "Last Name": "",
            "Addr Line1": "5254 Frechmans Ridge",
            "City": "Fort Benton",
            "State": "MT",
            "Zip": "59442",
            "Zip4": "",
            "Expenditure Type": "All Other Expenditures",
            "Amount": 75.35,
            "Purpose": "convention meeting",
            "Election Type": "General",
            "Expenditure Paid Communications Platform": "",
            "Expenditure Paid Communications Quantity": "",
            "Expenditure Paid Communications Subject Matter": ""
        },
        {
            "Date Paid": "04/06/15",
            "Entity Name": "K Hanson 5 Inc.",
            "First Name": "",
            "Middle Initial": "",
            "Last Name": "",
            "Addr Line1": "PO Box 1047",
            "City": "Chinook",
            "State": "MT",
            "Zip": "59523",
            "Zip4": "",
            "Expenditure Type": "All Other Expenditures",
            "Amount": 40.61,
            "Purpose": "Lincoln Day Dinner ad",
            "Election Type": "General",
            "Expenditure Paid Communications Platform": "",
            "Expenditure Paid Communications Quantity": "",
            "Expenditure Paid Communications Subject Matter": ""
        },
        {
            "Date Paid": "01/28/15",
            "Entity Name": "Montana GOP",
            "First Name": "",
            "Middle Initial": "",
            "Last Name": "",
            "Addr Line1": "PO Box 935",
            "City": "Helena",
            "State": "MT",
            "Zip": "59624",
            "Zip4": "",
            "Expenditure Type": "All Other Expenditures",
            "Amount": 200.0,
            "Purpose": "Montana GOP donation - re-imburse",
            "Election Type": "Primary",
            "Expenditure Paid Communications Platform": "",
            "Expenditure Paid Communications Quantity": "",
            "Expenditure Paid Communications Subject Matter": ""
        },
        {
            "Date Paid": "02/19/15",
            "Entity Name": "Montana Outback wireless",
            "First Name": "",
            "Middle Initial": "",
            "Last Name": "",
            "Addr Line1": "PO Box 1047",
            "City": "Fort Benton",
            "State": "MT",
            "Zip": "59442",
            "Zip4": "",
            "Expenditure Type": "All Other Expenditures",
            "Amount": 200.0,
            "Purpose": "Sykpe fee",
            "Election Type": "General",
            "Expenditure Paid Communications Platform": "",
            "Expenditure Paid Communications Quantity": "",
            "Expenditure Paid Communications Subject Matter": ""
        },
        {
            "Date Paid": "01/27/15",
            "Entity Name": "River & Plain Society",
            "First Name": "",
            "Middle Initial": "",
            "Last Name": "",
            "Addr Line1": "PO Box 262",
            "City": "Fort Benton",
            "State": "MT",
            "Zip": "59442",
            "Zip4": "",
            "Expenditure Type": "All Other Expenditures",
            "Amount": 250.0,
            "Purpose": "rental for fundraiser venue",
            "Election Type": "General",
            "Expenditure Paid Communications Platform": "",
            "Expenditure Paid Communications Quantity": "",
            "Expenditure Paid Communications Subject Matter": ""
        },
        {
            "Date Paid": "02/15/15",
            "Entity Name": "Straight Shooters",
            "First Name": "",
            "Middle Initial": "",
            "Last Name": "",
            "Addr Line1": "750 6th St SW",
            "City": "Great Falls",
            "State": "MT",
            "Zip": "59401",
            "Zip4": "",
            "Expenditure Type": "All Other Expenditures",
            "Amount": 400.0,
            "Purpose": "Lincoln Day Dinner Auction items",
            "Election Type": "General",
            "Expenditure Paid Communications Platform": "",
            "Expenditure Paid Communications Quantity": "",
            "Expenditure Paid Communications Subject Matter": ""
        },
        {
            "Date Paid": "02/09/15",
            "Entity Name": "The Riverpress",
            "First Name": "",
            "Middle Initial": "",
            "Last Name": "",
            "Addr Line1": "1408 Front St.",
            "City": "Fort Benton",
            "State": "MT",
            "Zip": "59442",
            "Zip4": "",
            "Expenditure Type": "All Other Expenditures",
            "Amount": 30.0,
            "Purpose": "ADVERTISING - Lincoln Reagan Dinner",
            "Election Type": "General",
            "Expenditure Paid Communications Platform": "",
            "Expenditure Paid Communications Quantity": "",
            "Expenditure Paid Communications Subject Matter": ""
        },
        {
            "Date Paid": "09/03/15",
            "Entity Name": "The Riverpress",
            "First Name": "",
            "Middle Initial": "",
            "Last Name": "",
            "Addr Line1": "1408 Front St.",
            "City": "Fort Benton",
            "State": "MT",
            "Zip": "59442",
            "Zip4": "",
            "Expenditure Type": "All Other Expenditures",
            "Amount": 31.5,
            "Purpose": "Meeting Ads",
            "Election Type": "General",
            "Expenditure Paid Communications Platform": "",
            "Expenditure Paid Communications Quantity": "",
            "Expenditure Paid Communications Subject Matter": ""
        },
        {
            "Date Paid": "02/26/15",
            "Entity Name": "The Riverpress",
            "First Name": "",
            "Middle Initial": "",
            "Last Name": "",
            "Addr Line1": "1408 Front St.",
            "City": "Fort Benton",
            "State": "MT",
            "Zip": "59442",
            "Zip4": "",
            "Expenditure Type": "All Other Expenditures",
            "Amount": 54.0,
            "Purpose": "ADVERTISE IN NEWSPAPER",
            "Election Type": "General",
            "Expenditure Paid Communications Platform": "",
            "Expenditure Paid Communications Quantity": "",
            "Expenditure Paid Communications Subject Matter": ""
        },
        {
            "Date Paid": "04/12/15",
            "Entity Name": "Vicky O'Hara",
            "First Name": "",
            "Middle Initial": "",
            "Last Name": "",
            "Addr Line1": "5254 Frechmans Ridge",
            "City": "Fort Benton",
            "State": "MT",
            "Zip": "59442",
            "Zip4": "",
            "Expenditure Type": "All Other Expenditures",
            "Amount": 110.0,
            "Purpose": "PRINTING Lincoln day dinner invitations",
            "Election Type": "General",
            "Expenditure Paid Communications Platform": "",
            "Expenditure Paid Communications Quantity": "",
            "Expenditure Paid Communications Subject Matter": ""
        },
        {
            "Date Paid": "03/06/15",
            "Entity Name": "Vicky O'Hara",
            "First Name": "",
            "Middle Initial": "",
            "Last Name": "",
            "Addr Line1": "5254 Frechmans Ridge",
            "City": "Fort Benton",
            "State": "MT",
            "Zip": "59442",
            "Zip4": "",
            "Expenditure Type": "All Other Expenditures",
            "Amount": 287.83,
            "Purpose": "Reinbursement to Vicki O'Hara for LDD expenses",
            "Election Type": "General",
            "Expenditure Paid Communications Platform": "",
            "Expenditure Paid Communications Quantity": "",
            "Expenditure Paid Communications Subject Matter": ""
        },
        {
            "Date Paid": "02/22/15",
            "Entity Name": "Walmart",
            "First Name": "",
            "Middle Initial": "",
            "Last Name": "",
            "Addr Line1": "4000 Hwy 93 S.",
            "City": "Missoula",
            "State": "MT",
            "Zip": "59804",
            "Zip4": "",
            "Expenditure Type": "All Other Expenditures",
            "Amount": 13.94,
            "Purpose": "Thank You Notes",
            "Election Type": "General",
            "Expenditure Paid Communications Platform": "",
            "Expenditure Paid Communications Quantity": "",
            "Expenditure Paid Communications Subject Matter": ""
        },
        {
            "Date Paid": "12/03/15",
            "Entity Name": "Walmart",
            "First Name": "",
            "Middle Initial": "",
            "Last Name": "",
            "Addr Line1": "4000 Hwy 93 S.",
            "City": "Missoula",
            "State": "MT",
            "Zip": "59804",
            "Zip4": "",
            "Expenditure Type": "All Other Expenditures",
            "Amount": 131.42,
            "Purpose": "Summer Celebration float - candy",
            "Election Type": "General",
            "Expenditure Paid Communications Platform": "",
            "Expenditure Paid Communications Quantity": "",
            "Expenditure Paid Communications Subject Matter": ""
        }
    ]
}