{
    "summary": {
        "previous report": {
            "primary": 0.0,
            "general": 0.0,
            "total": 0.0
        },
        "Receipts": {
            "primary": 345.0,
            "general": 0.0,
            "total": 345.0
        },
        "Expenditures": {
            "primary": 155.0,
            "general": 0.0,
            "total": 155.0
        },
        "Ending Balance": {
            "primary": 190.0,
            "general": 0.0,
            "total": 190.0
        },
        "report_start_date": "01/01/2020",
        "report_end_date": "03/15/2020"
    },
    "contributions": "[{\"Date Paid\":\"03\\/12\\/2020\",\"Entity Name\":null,\"First Name\":\"Sally\",\"Middle Initial\":null,\"Last Name\":\"Tucker\",\"Addr Line1\":\"1915 Montana Ave\",\"City\":\"Black Eagle\",\"State\":\"MT\",\"Zip\":59414,\"Zip4\":null,\"Country\":null,\"Occupation\":\"RETIRED \",\"Employer\":\"Retired\",\"Contribution Type\":3,\"Amount\":144.18,\"Amount Type\":\"IK\",\"Purpose\":\"Purchase of website, website builder, website hosting GoDaddy.com\",\"Election Type\":\"PM\",\"Total Primary\":244.18,\"Total General\":0,\"Refund Transaction Type\":null,\"Refund Original Transaction Date\":null,\"Refund Original Transaction Total\":null,\"Refund Original Transaction Descr\":null,\"Previous Transaction (Y\\/N)\":\"N\",\"Fundraiser Name\":null,\"Fundraiser Location\":null,\"Fundraiser Attendees\":null,\"Fundraiser Tickets Sold\":null},{\"Date Paid\":\"02\\/01\\/2020\",\"Entity Name\":null,\"First Name\":\"Sally\",\"Middle Initial\":null,\"Last Name\":\"Tucker\",\"Addr Line1\":\"1915 Montana Ave\",\"City\":\"Black Eagle\",\"State\":\"MT\",\"Zip\":59414,\"Zip4\":null,\"Country\":null,\"Occupation\":\"Retired\",\"Employer\":\"Retired\",\"Contribution Type\":3,\"Amount\":100.0,\"Amount Type\":\"IK\",\"Purpose\":\"Payment for logo graphic design Bara Designs\",\"Election Type\":\"PM\",\"Total Primary\":244.18,\"Total General\":0,\"Refund Transaction Type\":null,\"Refund Original Transaction Date\":null,\"Refund Original Transaction Total\":null,\"Refund Original Transaction Descr\":null,\"Previous Transaction (Y\\/N)\":\"N\",\"Fundraiser Name\":null,\"Fundraiser Location\":null,\"Fundraiser Attendees\":null,\"Fundraiser Tickets Sold\":null},{\"Date Paid\":\"02\\/26\\/2020\",\"Entity Name\":null,\"First Name\":\"Sally\",\"Middle Initial\":null,\"Last Name\":\"Tucker\",\"Addr Line1\":\"1915 Montana Ave\",\"City\":\"Black Eagle\",\"State\":\"MT\",\"Zip\":59414,\"Zip4\":null,\"Country\":null,\"Occupation\":\"RETIRED \",\"Employer\":\"Retired\",\"Contribution Type\":3,\"Amount\":155.0,\"Amount Type\":\"IK\",\"Purpose\":\"Payment for art pieces by L. Lineberry to Gallery 16\",\"Election Type\":\"PM\",\"Total Primary\":244.18,\"Total General\":0,\"Refund Transaction Type\":null,\"Refund Original Transaction Date\":null,\"Refund Original Transaction Total\":null,\"Refund Original Transaction Descr\":null,\"Previous Transaction (Y\\/N)\":\"N\",\"Fundraiser Name\":null,\"Fundraiser Location\":null,\"Fundraiser Attendees\":null,\"Fundraiser Tickets Sold\":null},{\"Date Paid\":\"02\\/20\\/2020\",\"Entity Name\":null,\"First Name\":\"Gary\",\"Middle Initial\":null,\"Last Name\":\"Sorum\",\"Addr Line1\":\"724 27 Ave NE\",\"City\":\"Great Falls\",\"State\":\"MT\",\"Zip\":59404,\"Zip4\":null,\"Country\":null,\"Occupation\":\"Landlord\",\"Employer\":\"Self-Employed \",\"Contribution Type\":9,\"Amount\":50.0,\"Amount Type\":\"CA\",\"Purpose\":null,\"Election Type\":\"PM\",\"Total Primary\":50.0,\"Total General\":0,\"Refund Transaction Type\":null,\"Refund Original Transaction Date\":null,\"Refund Original Transaction Total\":null,\"Refund Original Transaction Descr\":null,\"Previous Transaction (Y\\/N)\":\"N\",\"Fundraiser Name\":null,\"Fundraiser Location\":null,\"Fundraiser Attendees\":null,\"Fundraiser Tickets Sold\":null},{\"Date Paid\":\"02\\/13\\/2020\",\"Entity Name\":null,\"First Name\":\"Darlene\",\"Middle Initial\":null,\"Last Name\":\"Meddock\",\"Addr Line1\":\"1245 Park Garden Rd\",\"City\":\"Great Falls\",\"State\":\"MT\",\"Zip\":59404,\"Zip4\":null,\"Country\":null,\"Occupation\":\"Landlord\",\"Employer\":\"Self-Employed \",\"Contribution Type\":9,\"Amount\":50.0,\"Amount Type\":\"CA\",\"Purpose\":null,\"Election Type\":\"PM\",\"Total Primary\":50.0,\"Total General\":0,\"Refund Transaction Type\":null,\"Refund Original Transaction Date\":null,\"Refund Original Transaction Total\":null,\"Refund Original Transaction Descr\":null,\"Previous Transaction (Y\\/N)\":\"N\",\"Fundraiser Name\":null,\"Fundraiser Location\":null,\"Fundraiser Attendees\":null,\"Fundraiser Tickets Sold\":null},{\"Date Paid\":\"01\\/31\\/2020\",\"Entity Name\":null,\"First Name\":\"Theresa\",\"Middle Initial\":null,\"Last Name\":\"Manzella\",\"Addr Line1\":\"640 Gold Creek Loop\",\"City\":\"Hamilton\",\"State\":\"MT\",\"Zip\":59840,\"Zip4\":null,\"Country\":null,\"Occupation\":\"Horse Trainer \",\"Employer\":\"Self-Employed \",\"Contribution Type\":9,\"Amount\":100.0,\"Amount Type\":\"CA\",\"Purpose\":null,\"Election Type\":\"PM\",\"Total Primary\":100.0,\"Total General\":0,\"Refund Transaction Type\":null,\"Refund Original Transaction Date\":null,\"Refund Original Transaction Total\":null,\"Refund Original Transaction Descr\":null,\"Previous Transaction (Y\\/N)\":\"N\",\"Fundraiser Name\":null,\"Fundraiser Location\":null,\"Fundraiser Attendees\":null,\"Fundraiser Tickets Sold\":null},{\"Date Paid\":\"01\\/23\\/2020\",\"Entity Name\":null,\"First Name\":\"Kristen\",\"Middle Initial\":null,\"Last Name\":\"Juras\",\"Addr Line1\":\"220 Woodland Estates\",\"City\":\"Great Falls\",\"State\":\"MT\",\"Zip\":59404,\"Zip4\":null,\"Country\":null,\"Occupation\":\"Attorney\",\"Employer\":\"Self-Employed\",\"Contribution Type\":9,\"Amount\":100.0,\"Amount Type\":\"CA\",\"Purpose\":null,\"Election Type\":\"PM\",\"Total Primary\":100.0,\"Total General\":0,\"Refund Transaction Type\":null,\"Refund Original Transaction Date\":null,\"Refund Original Transaction Total\":null,\"Refund Original Transaction Descr\":null,\"Previous Transaction (Y\\/N)\":\"N\",\"Fundraiser Name\":null,\"Fundraiser Location\":null,\"Fundraiser Attendees\":null,\"Fundraiser Tickets Sold\":null}]",
    "expenditures": "[]",
    "unitemized_contributions": 45.0
}